bfebdfa2e2cb0f9d4f34__mypyc.cp310-win_amd64.pyd
cli.cp310-win_amd64.pyd
exceptions.cp310-win_amd64.pyd
settings.cp310-win_amd64.pyd
version.cp310-win_amd64.pyd
futures/enums.cp310-win_amd64.pyd
futures/future.cp310-win_amd64.pyd
futures/results.cp310-win_amd64.pyd
futures/store.cp310-win_amd64.pyd
monads/either.cp310-win_amd64.pyd
pandos/cli.py
pandos/exceptions.py
pandos/maturity.py
pandos/settings.py
pandos/version
pandos/version.py
pandos/futures/__init__.py
pandos/futures/enums.py
pandos/futures/future.py
pandos/futures/results.py
pandos/futures/store.py
pandos/monads/__init__.py
pandos/monads/either.py
pandos/utils/__init__.py
pandos/utils/custom_enum_types.py
pandos/utils/pyobj_serializers.py
pandos-0.4.0.data/scripts/pandos
utils/custom_enum_types.cp310-win_amd64.pyd
utils/pyobj_serializers.cp310-win_amd64.pyd
pandos-0.4.0.dist-info/LICENSE
pandos-0.4.0.dist-info/METADATA
pandos-0.4.0.dist-info/WHEEL
pandos-0.4.0.dist-info/top_level.txt
pandos-0.4.0.dist-info/RECORD
