Metadata-Version: 2.1
Name: pandos
Version: 0.4.0
Summary: The `pandos core` package contains the baseline implementation of the pandos base abstractions.
Home-page: https://github.com/pando-systems/pandos
Author: rhdzmota
Author-email: info@rhdzmota.com
License: /**
Classifier: Development Status :: 2 - Pre-Alpha
Classifier: Typing :: Typed
Classifier: Topic :: Scientific/Engineering
Classifier: Topic :: System :: Distributed Computing
Classifier: Topic :: Scientific/Engineering :: Artificial Intelligence
Classifier: Topic :: Software Development :: Libraries :: Python Modules
Classifier: Programming Language :: Python :: 3 :: Only
Classifier: Programming Language :: Python :: 3.10
Requires-Python: >=3.10, <4
License-File: LICENSE
Requires-Dist: fire ==0.5.0
Requires-Dist: requests ==2.31.0
Requires-Dist: dill ==0.3.7
